hyphen/__init__.py
hyphen/dictools.py
hyphen/hnj.pyd
hyphen/hyphenator.py
hyphen/textwrap2.py
PyHyphen-4.0.4.dist-info/AUTHORS
PyHyphen-4.0.4.dist-info/LICENSE.txt
PyHyphen-4.0.4.dist-info/METADATA
PyHyphen-4.0.4.dist-info/WHEEL
PyHyphen-4.0.4.dist-info/top_level.txt
PyHyphen-4.0.4.dist-info/RECORD
