Metadata-Version: 2.1
Name: PyHyphen
Version: 4.0.4
Summary: The hyphenation library of LibreOffice and FireFox wrapped for Python
Home-page: https://github.com/dr-leo/PyHyphen
Author: Dr. Leo & Regis Behmo
Author-email: fhaxbox66@googlemail.com
Classifier: Intended Audience :: Developers
Classifier: License :: OSI Approved :: Apache Software License
Classifier: Development Status :: 4 - Beta
Classifier: Operating System :: OS Independent
Classifier: Programming Language :: Python
Classifier: Programming Language :: Python :: 3.7
Classifier: Programming Language :: Python :: 3.8
Classifier: Programming Language :: Python :: 3.9
Classifier: Programming Language :: C
Classifier: Topic :: Text Processing
Classifier: Topic :: Text Processing :: Linguistic
License-File: LICENSE.txt
License-File: AUTHORS
Requires-Dist: wheel >=0.40.0
Requires-Dist: setuptools >=68.0
Requires-Dist: appdirs >=1.4.0
Requires-Dist: requests >=2.25
